colorgradtext/__init__.py
colorgradtext/gradients.py
colorgradtext/utils.py
colorgradtext-1.0.0.dist-info/licenses/LICENSE
colorgradtext-1.0.0.dist-info/METADATA
colorgradtext-1.0.0.dist-info/WHEEL
colorgradtext-1.0.0.dist-info/top_level.txt
colorgradtext-1.0.0.dist-info/RECORD
