Metadata-Version: 2.4
Name: colorgradtext
Version: 1.0.0
Summary: Apply amazing horizontal and vertical color gradients to text and ASCII art in the terminal.
Author: Og_Ten
License: MIT
Project-URL: Homepage, https://github.com/yourusername/colorgradtext
Project-URL: Issues, https://github.com/yourusername/colorgradtext/issues
Keywords: text,gradient,ansi,colors,terminal
Classifier: Programming Language :: Python :: 3
Classifier: License :: OSI Approved :: MIT License
Classifier: Operating System :: OS Independent
Requires-Python: >=3.8
License-File: LICENSE
Dynamic: license-file
